pelican/plugins/webassets/__init__.py
pelican/plugins/webassets/webassets.py
pelican/plugins/webassets/vendor/__init__.py
pelican/plugins/webassets/vendor/webassets/__init__.py
pelican/plugins/webassets/vendor/webassets/bundle.py
pelican/plugins/webassets/vendor/webassets/cache.py
pelican/plugins/webassets/vendor/webassets/env.py
pelican/plugins/webassets/vendor/webassets/exceptions.py
pelican/plugins/webassets/vendor/webassets/importlib.py
pelican/plugins/webassets/vendor/webassets/loaders.py
pelican/plugins/webassets/vendor/webassets/merge.py
pelican/plugins/webassets/vendor/webassets/py.typed
pelican/plugins/webassets/vendor/webassets/script.py
pelican/plugins/webassets/vendor/webassets/six.py
pelican/plugins/webassets/vendor/webassets/test.py
pelican/plugins/webassets/vendor/webassets/updater.py
pelican/plugins/webassets/vendor/webassets/utils.py
pelican/plugins/webassets/vendor/webassets/version.py
pelican/plugins/webassets/vendor/webassets/ext/__init__.py
pelican/plugins/webassets/vendor/webassets/ext/jinja2.py
pelican/plugins/webassets/vendor/webassets/filter/__init__.py
pelican/plugins/webassets/vendor/webassets/filter/autoprefixer.py
pelican/plugins/webassets/vendor/webassets/filter/babel.py
pelican/plugins/webassets/vendor/webassets/filter/cleancss.py
pelican/plugins/webassets/vendor/webassets/filter/clevercss.py
pelican/plugins/webassets/vendor/webassets/filter/closure.py
pelican/plugins/webassets/vendor/webassets/filter/closure_stylesheets.py
pelican/plugins/webassets/vendor/webassets/filter/closure_templates.py
pelican/plugins/webassets/vendor/webassets/filter/coffeescript.py
pelican/plugins/webassets/vendor/webassets/filter/compass.py
pelican/plugins/webassets/vendor/webassets/filter/cssmin.py
pelican/plugins/webassets/vendor/webassets/filter/cssprefixer.py
pelican/plugins/webassets/vendor/webassets/filter/cssutils.py
pelican/plugins/webassets/vendor/webassets/filter/datauri.py
pelican/plugins/webassets/vendor/webassets/filter/dust.py
pelican_webassets-2.1.0.dist-info/METADATA
pelican_webassets-2.1.0.dist-info/WHEEL
pelican_webassets-2.1.0.dist-info/RECORD
