Metadata-Version: 2.3
Name: pelican-webassets
Version: 2.1.0
Summary: Pelican plugin to manage web assets such as CSS and JS files
Project-URL: Funding, https://donate.getpelican.com/
Project-URL: Issue Tracker, https://github.com/pelican-plugins/webassets/issues
Author: Pelican Dev Team <authors@getpelican.com>
License-Expression: AGPL-3.0
Keywords: compilation,css,js,minimization,pelican,plugin,webassets
Classifier: Development Status :: 5 - Production/Stable
Classifier: Environment :: Console
Classifier: Framework :: Pelican
Classifier: Framework :: Pelican :: Plugins
Classifier: Intended Audience :: End Users/Desktop
Classifier: Operating System :: OS Independent
Classifier: Programming Language :: JavaScript
Classifier: Topic :: Internet :: WWW/HTTP
Classifier: Topic :: Software Development :: Build Tools
Classifier: Topic :: Software Development :: Code Generators
Classifier: Topic :: Software Development :: Compilers
Classifier: Topic :: Software Development :: Libraries :: Python Modules
Classifier: Topic :: Software Development :: Pre-processors
Classifier: Topic :: Software Development :: User Interfaces
Requires-Python: ~=3.9
Requires-Dist: pelican>=4.5
